swc_api/__init__.py
swc_api/swc_api.py
swc_api/swc_token.py
swc_api-0.1.8.dist-info/LICENSE.txt
swc_api-0.1.8.dist-info/METADATA
swc_api-0.1.8.dist-info/WHEEL
swc_api-0.1.8.dist-info/top_level.txt
swc_api-0.1.8.dist-info/RECORD
