Metadata-Version: 2.1
Name: swc-api
Version: 0.1.8
Summary: A library for interacting with the Small World Community REST API
Home-page: https://github.com/citizensclimateeducation/community_api
Author: Bryan Hermsen
Author-email: b_hermse@hotmail.com
License: MIT
Keywords: rest,requests
Platform: UNKNOWN
Classifier: Environment :: Console
Classifier: Intended Audience :: Information Technology
Classifier: Intended Audience :: Developers
Classifier: License :: OSI Approved :: MIT License
Classifier: Natural Language :: English
Classifier: Operating System :: OS Independent
Classifier: Programming Language :: Python :: 3.6
Classifier: Programming Language :: Python :: 3.7
Classifier: Programming Language :: Python :: 3.8
Classifier: Topic :: Software Development :: Libraries :: Python Modules
Classifier: Topic :: Utilities
Requires-Dist: requests (>=2.20)
Requires-Dist: requests-toolbelt (>=0.9)
